tests/__init__.py
tests/test_banner.py
tests/test_styler.py
tests/test_utils.py
textstyler/__init__.py
textstyler/banner.py
textstyler/styler.py
textstyler/utils.py
textstyler-0.1.dist-info/LICENSE
textstyler-0.1.dist-info/METADATA
textstyler-0.1.dist-info/WHEEL
textstyler-0.1.dist-info/top_level.txt
textstyler-0.1.dist-info/RECORD
