Metadata-Version: 2.1
Name: textstyler
Version: 0.1
Summary: A package for styling text and creating text banners
Home-page: https://github.com/PrestigeOcean1/textstyler
Author: Your Name
Author-email: dexterawesome16@gmail.com
Classifier: Programming Language :: Python :: 3
Classifier: License :: OSI Approved :: MIT License
Classifier: Operating System :: OS Independent
Requires-Python: >=3.6
License-File: LICENSE
Requires-Dist: termcolor
Requires-Dist: pyfiglet
